MANIFEST.in
README.txt
setup.py
docs/HISTORY.txt
docs/README.txt
src/ztfy/__init__.py
src/ztfy.blog.egg-info/PKG-INFO
src/ztfy.blog.egg-info/SOURCES.txt
src/ztfy.blog.egg-info/dependency_links.txt
src/ztfy.blog.egg-info/entry_points.txt
src/ztfy.blog.egg-info/namespace_packages.txt
src/ztfy.blog.egg-info/not-zip-safe
src/ztfy.blog.egg-info/requires.txt
src/ztfy.blog.egg-info/top_level.txt
src/ztfy/blog/__init__.py
src/ztfy/blog/blog.py
src/ztfy/blog/blog.zcml
src/ztfy/blog/category.py
src/ztfy/blog/category.zcml
src/ztfy/blog/configure.zcml
src/ztfy/blog/database.py
src/ztfy/blog/google.py
src/ztfy/blog/google.zcml
src/ztfy/blog/layer.py
src/ztfy/blog/link.py
src/ztfy/blog/link.zcml
src/ztfy/blog/overrides.zcml
src/ztfy/blog/paragraph.py
src/ztfy/blog/resource.py
src/ztfy/blog/resource.zcml
src/ztfy/blog/section.py
src/ztfy/blog/section.zcml
src/ztfy/blog/security.py
src/ztfy/blog/security.zcml
src/ztfy/blog/site.py
src/ztfy/blog/site.zcml
src/ztfy/blog/skin.py
src/ztfy/blog/topic.py
src/ztfy/blog/topic.zcml
src/ztfy/blog/vocabulary.py
src/ztfy/blog/workflow.py
src/ztfy/blog/browser/__init__.py
src/ztfy/blog/browser/blog.py
src/ztfy/blog/browser/blog.zcml
src/ztfy/blog/browser/category.py
src/ztfy/blog/browser/category.zcml
src/ztfy/blog/browser/configure.zcml
src/ztfy/blog/browser/google.py
src/ztfy/blog/browser/link.py
src/ztfy/blog/browser/link.zcml
src/ztfy/blog/browser/paragraph.py
src/ztfy/blog/browser/paragraph.zcml
src/ztfy/blog/browser/resource.py
src/ztfy/blog/browser/resource.zcml
src/ztfy/blog/browser/section.py
src/ztfy/blog/browser/section.zcml
src/ztfy/blog/browser/site.py
src/ztfy/blog/browser/site.zcml
src/ztfy/blog/browser/skin.py
src/ztfy/blog/browser/topic.py
src/ztfy/blog/browser/topic.zcml
src/ztfy/blog/browser/workflow.py
src/ztfy/blog/browser/workflow.zcml
src/ztfy/blog/browser/interfaces/__init__.py
src/ztfy/blog/browser/interfaces/paragraph.py
src/ztfy/blog/browser/interfaces/skin.py
src/ztfy/blog/browser/json/__init__.py
src/ztfy/blog/browser/json/configure.zcml
src/ztfy/blog/browser/json/container.py
src/ztfy/blog/browser/json/site.py
src/ztfy/blog/browser/resources/img/search.png
src/ztfy/blog/browser/resources/js/ztfy.blog.back.js
src/ztfy/blog/browser/resources/js/ztfy.blog.back.min.js
