Metadata-Version: 1.1
Name: ztfy.blog
Version: 0.6.1
Summary: ZTFY blog handling package
Home-page: http://www.ztfy.org
Author: Thierry Florac
Author-email: tflorac@ulthar.net
License: ZPL
Keywords: ZTFY Zope3 blog package
Platform: UNKNOWN
Classifier: License :: OSI Approved :: Zope Public License
Classifier: Development Status :: 4 - Beta
Classifier: Programming Language :: Python
Classifier: Framework :: Zope3
Classifier: Topic :: Software Development :: Libraries :: Python Modules
